<?xml version="1.0" encoding="UTF-8"?>
<activity id="53" moduleid="133783" modulename="workshop" contextid="204183">
  <workshop id="53">
    <name>In-class problem: inelastic collision</name>
    <intro>&lt;p&gt;This will be our first attempt at working a problem in class in groups.  The problem has been designed to be quick to do, and straightforward to mark since you will be marking it.&lt;/p&gt;</intro>
    <introformat>1</introformat>
    <instructauthors>&lt;h2 class="western"&gt;Objectives&lt;/h2&gt;
&lt;ol&gt;
&lt;li class="western"&gt;Students will write down knows and unknowns for a collision.&lt;/li&gt;
&lt;li class="western"&gt;Students will solve for unknowns using conservation of momentum and the definition of coefficient of restitution.&lt;/li&gt;
&lt;/ol&gt;
&lt;p class="western"&gt;As shown in the diagram, in a test of materials strength, a 50 g ball bearing collides with a 1.2 kg steel plate. The ball bearing was going at 30 m/s to the right before the collision and the steel plate was stationary. The steel plate had been held stationary until just before the collision, but it was released milliseconds before the ball bearing hits it so that the collision is very nearly isolated. The coefficient of restitution for the collision is 0.80. Use the axes defined in the diagram.&lt;/p&gt;
&lt;p class="western"&gt;&lt;img src="@@PLUGINFILE@@/ball_bearing_at_steel_plate.png" width="400" height="338" alt="ball bearing hitting steel plate" /&gt;&lt;img src="@@PLUGINFILE@@/orange_xy_axes.png?time=1602687930109" width="150" height="167" alt="axes" /&gt;&lt;/p&gt;
&lt;p class="western"&gt;a) Define variables and in terms of your defined variables obtain an expression for the x-component of velocity of the ball bearing just after the collision. &lt;b&gt;Note: you do not have to find the velocity of the plate.&lt;/b&gt;&lt;/p&gt;
&lt;p class="western"&gt;&lt;/p&gt;
&lt;p class="western"&gt;b) Find the numerical value of the x-component of velocity of the ball bearing after the collision.&lt;/p&gt;</instructauthors>
    <instructauthorsformat>1</instructauthorsformat>
    <instructreviewers>&lt;p&gt;You will assess several (probably two) submissions by other people.  Follow the marking  guide.  The marking guide should be detailed enough that you won't have to use much judgement.&lt;/p&gt;</instructreviewers>
    <instructreviewersformat>1</instructreviewersformat>
    <timemodified>1620058139</timemodified>
    <phase>30</phase>
    <useexamples>0</useexamples>
    <usepeerassessment>1</usepeerassessment>
    <useselfassessment>0</useselfassessment>
    <grade>80.00000</grade>
    <gradinggrade>20.00000</gradinggrade>
    <strategy>accumulative</strategy>
    <evaluation>best</evaluation>
    <gradedecimals>0</gradedecimals>
    <submissiontypetext>0</submissiontypetext>
    <submissiontypefile>2</submissiontypefile>
    <nattachments>1</nattachments>
    <submissionfiletypes>.pdf</submissionfiletypes>
    <latesubmissions>0</latesubmissions>
    <maxbytes>0</maxbytes>
    <examplesmode>2</examplesmode>
    <submissionstart>1634140800</submissionstart>
    <submissionend>1634144880</submissionend>
    <assessmentstart>0</assessmentstart>
    <assessmentend>0</assessmentend>
    <conclusion>&lt;p&gt;Thanks for participating in this activity.  Note that you will have received two marks.  One mark will be for your submission.  The other mark is for the quality of feedback you gave to the submissions you were asked to assess.  The grade for the quality of assessment is found by comparing your assessment with the assessments of others who marked the same submission.  If you all agree on the grade then you get a perfect mark for your assessment.&lt;/p&gt;</conclusion>
    <conclusionformat>1</conclusionformat>
    <overallfeedbackmode>1</overallfeedbackmode>
    <overallfeedbackfiles>0</overallfeedbackfiles>
    <overallfeedbackfiletypes></overallfeedbackfiletypes>
    <overallfeedbackmaxbytes>0</overallfeedbackmaxbytes>
    <subplugin_workshopform_accumulative_workshop>
      <workshopform_accumulative_dimension id="161">
        <sort>1</sort>
        <description>&lt;p&gt;They should have started by writing down the knowns and unknowns, defining symbols as they do so.  What symbols they have chosen is unimportant as long as they are clear.  What they &lt;strong&gt;shouldn't have done&lt;/strong&gt; is just use one symbol (like m), for the inertias of both objects.  They need a different symbol for each inertia and different symbols for initial and final velocities of both objects.  They also need to use consistent units.  Here's how I would do it:&lt;/p&gt;
&lt;p&gt;m&lt;sub&gt;&lt;span style="font-size: 8.33333px;"&gt;b&lt;/span&gt;&lt;/sub&gt; = 0.050 kg    (ball)&lt;/p&gt;
&lt;p&gt;m&lt;sub&gt;P&lt;/sub&gt; = 1.2 kg       (plate)&lt;/p&gt;
&lt;p&gt;v&lt;sub&gt;bix&lt;/sub&gt; = 30 m/s    &lt;/p&gt;
&lt;p&gt;v&lt;sub&gt;Pix&lt;/sub&gt; = 0            (They might not even bother to write this down.  That's fine.)&lt;/p&gt;
&lt;p&gt;v&lt;sub&gt;bfx&lt;/sub&gt; = ?&lt;/p&gt;
&lt;p&gt;v&lt;sub&gt;Pfx&lt;/sub&gt; = ?&lt;/p&gt;
&lt;p&gt;e = 0.80     (Coefficient of restitution.  They might not have bothered to write this down.  That's OK.)&lt;/p&gt;
&lt;p&gt;Define clear symbols - 1 mark&lt;/p&gt;
&lt;p&gt;Didn't clearly define symbols - 0 marks&lt;/p&gt;</description>
        <descriptionformat>1</descriptionformat>
        <grade>1</grade>
        <weight>1</weight>
      </workshopform_accumulative_dimension>
      <workshopform_accumulative_dimension id="162">
        <sort>2</sort>
        <description>&lt;p&gt;They need to write down a conservation  of momentum equation.  Again, don't be picky about the symbols, as long as they stick with the symbols they defined earlier.  If they didn't clearly define symbols, but at this point write what appears to be a correct equation, then they should get part marks.&lt;/p&gt;
&lt;p&gt;In terms of my symbols the equation would be&lt;/p&gt;
&lt;p&gt;\( m_b v_{bix} + m_P v_{Pix} = m_b v_{bfx} + m_P v_{Pfx} \)&lt;/p&gt;
&lt;p&gt;but  since \(v_{2ix} = 0 \) they might have gone straight to writing it down as&lt;/p&gt;
&lt;p&gt;\( m_b v_{bix} = m_b v_{bfx} + m_P v_{Pfx} \)&lt;/p&gt;
&lt;p&gt;which is absolutely fine.&lt;/p&gt;
&lt;p&gt;Correct equation, written in terms of symbols defined earlier - 2 marks&lt;/p&gt;
&lt;p&gt;Correct equation (or equation which appears correct  giving  benefit of doubt), but either consistent symbols were not used, or they had not defined their symbols earlier - 1 mark&lt;/p&gt;
&lt;p&gt;No equation, or incorrect  equation, or choice of symbols is so unclear that you can't tell whether the equation is correct - 0 marks&lt;/p&gt;</description>
        <descriptionformat>1</descriptionformat>
        <grade>2</grade>
        <weight>1</weight>
      </workshopform_accumulative_dimension>
      <workshopform_accumulative_dimension id="163">
        <sort>3</sort>
        <description>&lt;p&gt;They need to have used the definition of the coefficient of restitution to get a second equation.  There are several ways they may have written this, such as&lt;/p&gt;
&lt;p&gt;\( v_{Pfx} - v_{bfx} = -e (v_{Pix} - v_{bix}) \)&lt;/p&gt;
&lt;p&gt;or perhaps&lt;/p&gt;
&lt;p&gt;\( e = - \frac{v_{Pfx} - v_{bfx}}{v_{Pix} - v_{bix}} \) &lt;/p&gt;
&lt;p&gt;All of  the parts involving \( v_{Pix} \) could have just been left out entirely since it is zero.  If  they have done that then that is perfectly fine.&lt;/p&gt;
&lt;p&gt;Wrote a correct equation relating initial x-comp. of relative velocity to final, using coefficient of restitution - 2 marks&lt;/p&gt;
&lt;p&gt;Attempt to relate velocities with coefficient of restitution, but equation incorrect - 1 mark&lt;/p&gt;
&lt;p&gt;No attempt to relate velocities with coefficient of restitution - 0 marks&lt;/p&gt;</description>
        <descriptionformat>1</descriptionformat>
        <grade>2</grade>
        <weight>1</weight>
      </workshopform_accumulative_dimension>
      <workshopform_accumulative_dimension id="164">
        <sort>4</sort>
        <description>&lt;p&gt;They now need to (symbolically) solve for the unknown final velocity component of the ball.  They should get something similar to&lt;/p&gt;
&lt;p&gt;\( v_{bfx} = \frac{m_b v_{bix} - e m_P v_{bix}}{m_b + m_P} \)&lt;/p&gt;
&lt;p&gt;or&lt;/p&gt;
&lt;p&gt;\( v_{bfx} = \frac{m_b - em_P}{m_b + m_P}v_{bix} \)&lt;/p&gt;
&lt;p&gt;Equation correctly solved for v&lt;sub&gt;bfx&lt;/sub&gt; - 1 mark&lt;/p&gt;
&lt;p&gt;Algebraic errors lead to wrong expression, or did not solve symbolically before putting in values - 0 marks&lt;/p&gt;</description>
        <descriptionformat>1</descriptionformat>
        <grade>1</grade>
        <weight>1</weight>
      </workshopform_accumulative_dimension>
      <workshopform_accumulative_dimension id="165">
        <sort>5</sort>
        <description>&lt;p&gt;Now we can plug in the numbers and enter the expression into  our calculator.  They don't really need to have shown much for this process.  If they got the correct expression then they might have been comfortable enough to just enter it all into their calculator without writing  it down.  That's fine.  Also, it doesn't matter whether they worked in kg or g, as long as they were consistent working in one or the other.  Entering in the values, I get&lt;/p&gt;
&lt;p&gt;\( v_{bfx} = \frac{(0.05 \, \textrm{kg})(30 \, \textrm{m/s}) - 0.8 (1.2 \, \textrm{kg})(30 \, \textrm{m/s})}{1.25 kg} \)&lt;/p&gt;
&lt;p&gt;= -21.8 m/s&lt;/p&gt;
&lt;p&gt;Note that the negative sign is important!  It indicates that the ball "recoils" and moves in the opposite direction from the way it was originally going.  &lt;/p&gt;
&lt;p&gt;Correct answer (including negative  sign) - 1 mark&lt;/p&gt;
&lt;p&gt;Incorrect answer - 0 marks&lt;/p&gt;</description>
        <descriptionformat>1</descriptionformat>
        <grade>1</grade>
        <weight>1</weight>
      </workshopform_accumulative_dimension>
    </subplugin_workshopform_accumulative_workshop>
    <subplugin_workshopform_comments_workshop>
    </subplugin_workshopform_comments_workshop>
    <subplugin_workshopform_numerrors_workshop>
    </subplugin_workshopform_numerrors_workshop>
    <subplugin_workshopform_rubric_workshop>
    </subplugin_workshopform_rubric_workshop>
    <subplugin_workshopeval_best_workshop>
      <workshopeval_best_settings>
        <comparison>5</comparison>
      </workshopeval_best_settings>
    </subplugin_workshopeval_best_workshop>
    <examplesubmissions>
      <examplesubmission id="526">
        <timecreated>1600223266</timecreated>
        <timemodified>1600223266</timemodified>
        <title>Sample, motion diagram and x vs. t graph</title>
        <content></content>
        <contentformat>1</contentformat>
        <contenttrust>0</contenttrust>
        <attachment>0</attachment>
        <referenceassessment id="1744">
          <timecreated>1600223364</timecreated>
          <timemodified>1600224247</timemodified>
          <grade>100.00000</grade>
          <feedbackauthor></feedbackauthor>
          <feedbackauthorformat>1</feedbackauthorformat>
          <feedbackauthorattachment>0</feedbackauthorattachment>
          <subplugin_workshopform_accumulative_referenceassessment>
            <workshopform_accumulative_referencegrade id="5129">
              <dimensionid>0</dimensionid>
              <grade>1.00000</grade>
              <peercomment></peercomment>
              <peercommentformat>0</peercommentformat>
            </workshopform_accumulative_referencegrade>
            <workshopform_accumulative_referencegrade id="5130">
              <dimensionid>161</dimensionid>
              <grade>1.00000</grade>
              <peercomment></peercomment>
              <peercommentformat>0</peercommentformat>
            </workshopform_accumulative_referencegrade>
            <workshopform_accumulative_referencegrade id="5131">
              <dimensionid>162</dimensionid>
              <grade>1.00000</grade>
              <peercomment></peercomment>
              <peercommentformat>0</peercommentformat>
            </workshopform_accumulative_referencegrade>
            <workshopform_accumulative_referencegrade id="5132">
              <dimensionid>163</dimensionid>
              <grade>1.00000</grade>
              <peercomment></peercomment>
              <peercommentformat>0</peercommentformat>
            </workshopform_accumulative_referencegrade>
          </subplugin_workshopform_accumulative_referenceassessment>
          <subplugin_workshopform_comments_referenceassessment>
          </subplugin_workshopform_comments_referenceassessment>
          <subplugin_workshopform_numerrors_referenceassessment>
          </subplugin_workshopform_numerrors_referenceassessment>
          <subplugin_workshopform_rubric_referenceassessment>
          </subplugin_workshopform_rubric_referenceassessment>
        </referenceassessment>
        <exampleassessments>
        </exampleassessments>
      </examplesubmission>
    </examplesubmissions>
    <submissions>
    </submissions>
    <aggregations>
    </aggregations>
  </workshop>
</activity>