<?xml version="1.0" encoding="UTF-8"?>
<inforef>
  <fileref>
    <file>
      <id>1713352</id>
    </file>
    <file>
      <id>1713353</id>
    </file>
    <file>
      <id>1713354</id>
    </file>
    <file>
      <id>1713355</id>
    </file>
    <file>
      <id>1713356</id>
    </file>
    <file>
      <id>1713357</id>
    </file>
    <file>
      <id>1713358</id>
    </file>
    <file>
      <id>1713359</id>
    </file>
    <file>
      <id>1713360</id>
    </file>
    <file>
      <id>1713361</id>
    </file>
    <file>
      <id>1713362</id>
    </file>
    <file>
      <id>1713363</id>
    </file>
    <file>
      <id>1713364</id>
    </file>
    <file>
      <id>1713365</id>
    </file>
    <file>
      <id>1713366</id>
    </file>
    <file>
      <id>1713367</id>
    </file>
    <file>
      <id>1713368</id>
    </file>
    <file>
      <id>1713369</id>
    </file>
  </fileref>
</inforef>