<?xml version="1.0" encoding="UTF-8"?>
<activity id="1731" moduleid="133720" modulename="feedback" contextid="204120">
  <feedback id="1731">
    <name>Instantaneous and average velocity (part 1)</name>
    <intro></intro>
    <introformat>1</introformat>
    <anonymous>2</anonymous>
    <email_notification>0</email_notification>
    <multiple_submit>0</multiple_submit>
    <autonumbering>0</autonumbering>
    <site_after_submit></site_after_submit>
    <page_after_submit></page_after_submit>
    <page_after_submitformat>1</page_after_submitformat>
    <publish_stats>1</publish_stats>
    <timeopen>0</timeopen>
    <timeclose>1632304800</timeclose>
    <timemodified>1632311383</timemodified>
    <completionsubmit>0</completionsubmit>
    <items>
      <item id="4235">
        <template>0</template>
        <name>label</name>
        <label></label>
        <presentation>&lt;p&gt;A rabbit runs north from point &lt;span style="color: #ff6600;"&gt;A&lt;/span&gt; to point &lt;span style="color: #ff6600;"&gt;B&lt;/span&gt; with uniform speed in 10 s.  It then suddenly turns and runs east at a new uniform speed to point &lt;span style="color: #ff6600;"&gt;C&lt;/span&gt; in 10 s.&lt;/p&gt;
&lt;p&gt;&lt;img src="@@PLUGINFILE@@/rabbit_run_north_then_east.png" alt="rabbit runs north then east" width="299" height="492" /&gt;&lt;/p&gt;
&lt;p&gt;What is the rabbit's &lt;strong&gt;average speed&lt;/strong&gt;?&lt;/p&gt;
&lt;p&gt; &lt;/p&gt;</presentation>
        <typ>label</typ>
        <hasvalue>0</hasvalue>
        <position>1</position>
        <required>0</required>
        <dependitem>0</dependitem>
        <dependvalue></dependvalue>
        <options></options>
      </item>
      <item id="4236">
        <template>0</template>
        <name></name>
        <label>answer</label>
        <presentation>r&gt;&gt;&gt;&gt;&gt;5 m/s
|3 m/s
|4 m/s
|3.5 m/s
|Not enough information</presentation>
        <typ>multichoice</typ>
        <hasvalue>1</hasvalue>
        <position>2</position>
        <required>1</required>
        <dependitem>0</dependitem>
        <dependvalue></dependvalue>
        <options>h</options>
      </item>
    </items>
    <completeds>
    </completeds>
  </feedback>
</activity>