<?xml version="1.0" encoding="UTF-8"?>
<activity id="1812" moduleid="133832" modulename="feedback" contextid="204232">
  <feedback id="1812">
    <name>Bug and Truck - 1</name>
    <intro>&lt;p&gt;&lt;/p&gt;
&lt;p&gt;&lt;/p&gt;</intro>
    <introformat>1</introformat>
    <anonymous>2</anonymous>
    <email_notification>0</email_notification>
    <multiple_submit>0</multiple_submit>
    <autonumbering>0</autonumbering>
    <site_after_submit></site_after_submit>
    <page_after_submit></page_after_submit>
    <page_after_submitformat>1</page_after_submitformat>
    <publish_stats>1</publish_stats>
    <timeopen>0</timeopen>
    <timeclose>1634724000</timeclose>
    <timemodified>1634732804</timemodified>
    <completionsubmit>0</completionsubmit>
    <items>
      <item id="4404">
        <template>0</template>
        <name>label</name>
        <label></label>
        <presentation>&lt;p&gt;&lt;img src="@@PLUGINFILE@@/bug_truck.png" alt="truck going  right, bug going left, collide" width="500" height="383" /&gt;&lt;/p&gt;
&lt;p&gt;A bug is traveling west when it hits the windshield of a truck traveling east on the highway.  The bug sticks to the windshield.  Is the momentum of the bug-truck system conserved &lt;strong&gt;in the bug’s reference frame?&lt;/strong&gt;&lt;/p&gt;</presentation>
        <typ>label</typ>
        <hasvalue>0</hasvalue>
        <position>1</position>
        <required>0</required>
        <dependitem>0</dependitem>
        <dependvalue></dependvalue>
        <options></options>
      </item>
      <item id="4405">
        <template>0</template>
        <name></name>
        <label>answer</label>
        <presentation>r&gt;&gt;&gt;&gt;&gt;Yes, the system is isolated, no matter what frame we observe it from.
|Yes, momentum is always conserved.
|No, because the bug accelerates during the collision.
|No, because the collision is completely inelastic.
|No, because the bug goes “SPLAT” and can’t observe the whole collision.</presentation>
        <typ>multichoice</typ>
        <hasvalue>1</hasvalue>
        <position>2</position>
        <required>1</required>
        <dependitem>0</dependitem>
        <dependvalue></dependvalue>
        <options>h</options>
      </item>
    </items>
    <completeds>
    </completeds>
  </feedback>
</activity>