<?xml version="1.0" encoding="UTF-8"?>
<activity id="1836" moduleid="133867" modulename="feedback" contextid="204267">
  <feedback id="1836">
    <name>Convert incoherent to coherent</name>
    <intro>&lt;p&gt;&lt;/p&gt;
&lt;p&gt;&lt;/p&gt;</intro>
    <introformat>1</introformat>
    <anonymous>2</anonymous>
    <email_notification>0</email_notification>
    <multiple_submit>0</multiple_submit>
    <autonumbering>0</autonumbering>
    <site_after_submit></site_after_submit>
    <page_after_submit></page_after_submit>
    <page_after_submitformat>1</page_after_submitformat>
    <publish_stats>1</publish_stats>
    <timeopen>0</timeopen>
    <timeclose>1635350400</timeclose>
    <timemodified>1635333799</timemodified>
    <completionsubmit>0</completionsubmit>
    <items>
      <item id="4452">
        <template>0</template>
        <name>label</name>
        <label></label>
        <presentation>&lt;p&gt;A system has some amount of incoherent energy.  Is it possible to convert this energy to coherent forms of energy?&lt;/p&gt;</presentation>
        <typ>label</typ>
        <hasvalue>0</hasvalue>
        <position>1</position>
        <required>0</required>
        <dependitem>0</dependitem>
        <dependvalue></dependvalue>
        <options></options>
      </item>
      <item id="4453">
        <template>0</template>
        <name></name>
        <label>answer</label>
        <presentation>r&gt;&gt;&gt;&gt;&gt;Yes, any form of energy can be converted to any other form.
|Yes, but only a portion of it can be converted to coherent forms.
|No.
|This question is incoherent.</presentation>
        <typ>multichoice</typ>
        <hasvalue>1</hasvalue>
        <position>2</position>
        <required>1</required>
        <dependitem>0</dependitem>
        <dependvalue></dependvalue>
        <options>h</options>
      </item>
    </items>
    <completeds>
    </completeds>
  </feedback>
</activity>